dtmodel/.env
dtmodel/__init__.py
dtmodel/app.py
dtmodel/base/__init__.py
dtmodel/base/_base.py
dtmodel/base/_imports.py
dtmodel/base/_types.py
dtmodel/base/base_enum.py
dtmodel/descriptor.py
dtmodel/endpoint/__init__.py
dtmodel/endpoint/base.py
dtmodel/endpoint/functions.py
dtmodel/endpoint/middleware.py
dtmodel/endpoint/path.py
dtmodel/endpoint/templates/__init__.py
dtmodel/endpoint/templates/detail.py
dtmodel/endpoint/templates/form.py
dtmodel/endpoint/templates/render.py
dtmodel/functions.py
dtmodel/micro/__init__.py
dtmodel/micro/_base.py
dtmodel/micro/_html.py
dtmodel/micro/_json.py
dtmodel/micro/dash.py
dtmodel/micro/primary.py
dtmodel/model.py
dtmodel/models/__init__.py
dtmodel/models/bases/__init__.py
dtmodel/models/bases/facility.py
dtmodel/models/bases/general.py
dtmodel/models/bases/medical.py
dtmodel/models/bases/people.py
dtmodel/models/bases/self_key.py
dtmodel/models/enums/__init__.py
dtmodel/models/enums/facility.py
dtmodel/models/enums/medical.py
dtmodel/models/enums/person.py
dtmodel/models/facility.py
dtmodel/models/medical.py
dtmodel/models/people.py
dtmodel/parse/__init__.py
dtmodel/parse/dates.py
dtmodel/parse/json_encoder.py
dtmodel/parse/null.py
dtmodel/parse/number.py
dtmodel/parse/string.py
dtmodel/parse/type_hint.py
dtmodel/regex.py
dtmodel-0.1.6.dist-info/entry_points.txt
dtmodel-0.1.6.dist-info/WHEEL
dtmodel-0.1.6.dist-info/METADATA
dtmodel-0.1.6.dist-info/RECORD
