Metadata-Version: 2.1
Name: dtmodel
Version: 0.1.6
Summary: 
Author: Daniel Arantes
Author-email: arantesdv@me.com
Requires-Python: >=3.9,<4.0
Classifier: Programming Language :: Python :: 3
Classifier: Programming Language :: Python :: 3.10
Classifier: Programming Language :: Python :: 3.9
Requires-Dist: Jinja2 (>=3.1.2,<4.0.0)
Requires-Dist: Unidecode (>=1.3.6,<2.0.0)
Requires-Dist: anyio (>=3.7.0,<4.0.0)
Requires-Dist: bcrypt (>=4.0.1,<5.0.0)
Requires-Dist: dtbase (>=0.0.5,<0.0.6)
Requires-Dist: itsdangerous (>=2.1.2,<3.0.0)
Requires-Dist: python-multipart (>=0.0.6,<0.0.7)
Requires-Dist: starlette (>=0.28.0,<0.29.0)
Requires-Dist: uvicorn (>=0.22.0,<0.23.0)
